easycord/__init__.py
easycord/bot.py
easycord/context.py
easycordx-0.1.0.dist-info/METADATA
easycordx-0.1.0.dist-info/WHEEL
easycordx-0.1.0.dist-info/top_level.txt
easycordx-0.1.0.dist-info/RECORD
