Metadata-Version: 2.4
Name: easycordx
Version: 0.1.0
Summary: A super beginner-friendly Python library for making Discord bots.
Author-email: LK-TEAM <unknownxd@email.com>
Classifier: Programming Language :: Python :: 3
Classifier: License :: OSI Approved :: MIT License
Classifier: Operating System :: OS Independent
Classifier: Topic :: Communications :: Chat
Classifier: Topic :: Software Development :: Libraries :: Python Modules
Requires-Python: >=3.8
Requires-Dist: disnake>=2.7.0
